{
  "$schema": "https://json-schema.org/draft/2020-12/schema",
  "$id": "https://familiar.dev/schemas/base/TaxonomyLevel.v1.schema.json",
  "title": "Base Taxonomy Level",
  "description": "The base schema for a file that defines a single level of the universal classification taxonomy. It is a collection of taxonomy nodes.",
  "type": "array",
  "minItems": 1,
  "items": {
    "$ref": "./BaseTaxonomyNode.schema.json"
  },
  "example": [
    {
      "id": "simple",
      "description": "For direct logging, immediate recording, and factual capture of events.",
      "label": "Simple",
      "level": "cognitive_complexity",
      "physics_profile_multiplier": "complexity_simple_v1",
      "search_method_affinity": "GraphQL"
    },
    {
      "id": "moderate",
      "description": "For pattern recognition, correlation analysis, and trend identification.",
      "label": "Moderate",
      "level": "cognitive_complexity",
      "physics_profile_multiplier": "complexity_moderate_v1",
      "search_method_affinity": "PgVectorScale"
    },
    {
      "id": "complex",
      "description": "For self-reflection, introspection, and meta-cognition. High quantum coherence requirements.",
      "label": "Complex",
      "level": "cognitive_complexity",
      "physics_profile_multiplier": "complexity_complex_v1",
      "search_method_affinity": "MemoryManifold"
    }
  ]
}
